tretool/__init__.py
tretool/config.py
tretool/decoratorlib.py
tretool/encoding.py
tretool/httplib.py
tretool/jsonlib.py
tretool/logger.py
tretool/mathlib.py
tretool/path.py
tretool/platformlib.py
tretool/plugin.py
tretool/smartCache.py
tretool/tasklib.py
tretool/timelib.py
tretool/ziplib.py
tretool/plugin/plu.py
tretool/transform/__init__.py
tretool/transform/docx.py
tretool/transform/pdf.py
tretool-1.0.0.dist-info/licenses/LICENSE
tretool-1.0.0.dist-info/METADATA
tretool-1.0.0.dist-info/WHEEL
tretool-1.0.0.dist-info/top_level.txt
tretool-1.0.0.dist-info/RECORD
