Metadata-Version: 2.4
Name: tretool
Version: 1.0.0
Summary: 一个有着许多功能的Python工具库
Author-email: Jemy <sh_ljr_2013@163.com>
License-Expression: MIT
Project-URL: Homepage, https://github.com/jemy/sampleproject
Project-URL: Issues, https://github.com/jemy/sampleproject/issues
Keywords: tool,tools,utility,utilities,productivity
Classifier: Programming Language :: Python :: 3
Classifier: Operating System :: OS Independent
Requires-Python: >=3.10
License-File: LICENSE
Provides-Extra: dev
Requires-Dist: pytest; extra == "dev"
Requires-Dist: pipreqs; extra == "dev"
Dynamic: license-file
